odoo/addons/account_promissory_note_cajamar/README.rst
odoo/addons/account_promissory_note_cajamar/__init__.py
odoo/addons/account_promissory_note_cajamar/__manifest__.py
odoo/addons/account_promissory_note_cajamar/i18n/account_promissory_note_cajamar.pot
odoo/addons/account_promissory_note_cajamar/i18n/es.po
odoo/addons/account_promissory_note_cajamar/models/__init__.py
odoo/addons/account_promissory_note_cajamar/models/account_journal.py
odoo/addons/account_promissory_note_cajamar/models/res_company.py
odoo/addons/account_promissory_note_cajamar/readme/CONFIGURE.rst
odoo/addons/account_promissory_note_cajamar/readme/CONTRIBUTORS.rst
odoo/addons/account_promissory_note_cajamar/readme/DESCRIPTION.rst
odoo/addons/account_promissory_note_cajamar/readme/USAGE.rst
odoo/addons/account_promissory_note_cajamar/report/__init__.py
odoo/addons/account_promissory_note_cajamar/report/account_promissory_note_writing_report.xml
odoo/addons/account_promissory_note_cajamar/report/check_print.py
odoo/addons/account_promissory_note_cajamar/static/description/icon.png
odoo/addons/account_promissory_note_cajamar/static/description/index.html
odoo/addons/account_promissory_note_cajamar/views/report_promissory_note.xml
odoo_addon_account_promissory_note_cajamar-15.0.1.0.0.3.dist-info/METADATA
odoo_addon_account_promissory_note_cajamar-15.0.1.0.0.3.dist-info/WHEEL
odoo_addon_account_promissory_note_cajamar-15.0.1.0.0.3.dist-info/top_level.txt
odoo_addon_account_promissory_note_cajamar-15.0.1.0.0.3.dist-info/RECORD
